{
   "order":{
      "id":606,
      "email":"customer_5@chefsteps.com",
      "closed_at":null,
      "created_at":"2016-09-01T12:51:09-07:00",
      "updated_at":"2016-09-01T14:30:03-07:00",
      "number":318,
      "note":null,
      "token":"0b31ee13f0f58defca1deb1f03e8c3db",
      "gateway":null,
      "test":false,
      "total_price":"0.00",
      "subtotal_price":"0.00",
      "total_weight":0,
      "total_tax":"0.00",
      "taxes_included":false,
      "currency":"USD",
      "financial_status":"paid",
      "confirmed":true,
      "total_discounts":"0.00",
      "total_line_items_price":"0.00",
      "cart_token":"6bfe0771c1a2b4e113e81dd735efab76",
      "buyer_accepts_marketing":false,
      "name":"#1318",
      "referring_site":"",
      "landing_site":"\/cart",
      "cancelled_at":null,
      "cancel_reason":null,
      "total_price_usd":"0.00",
      "checkout_token":"90492e5109287802e95dda6db0a4a153",
      "reference":null,
      "user_id":null,
      "location_id":null,
      "source_identifier":null,
      "source_url":null,
      "processed_at":"2016-09-01T12:51:09-07:00",
      "device_id":null,
      "browser_ip":null,
      "landing_site_ref":null,
      "order_number":1318,
      "discount_codes":[

      ],
      "note_attributes":[
         {
            "name":"utm",
            "value":"{}"
         },
         {
            "name":"ga",
            "value":"GA1.2.1112788629.1471381571"
         }
      ],
      "payment_gateway_names":[

      ],
      "processing_method":"free",
      "checkout_id":10295635783,
      "source_name":"web",
      "fulfillment_status":null,
      "tax_lines":[

      ],
      "tags":"",
      "contact_email":"customer_1@chefsteps.com",
      "order_status_url":"https:\/\/store.chocolateyshatner.com\/10875762\/checkouts\/90492e5109287802e95dda6db0a4a153\/thank_you_token?key=ce4de079136a354ac81852a8d2af887a",
      "line_items":[
         {
            "id":7903733191,
            "variant_id":28299978887,
            "title":"Shipwire Import Test",
            "quantity":1,
            "price":"0.00",
            "grams":0,
            "sku":"test10004",
            "variant_title":"",
            "vendor":"ChefSteps Staging",
            "fulfillment_service":"manual",
            "product_id":8690309639,
            "requires_shipping":true,
            "taxable":false,
            "gift_card":false,
            "pre_tax_price":"0.00",
            "name":"Shipwire Import Test",
            "variant_inventory_management":null,
            "properties":[

            ],
            "product_exists":true,
            "fulfillable_quantity":0,
            "total_discount":"0.00",
            "fulfillment_status":"pending",
            "tax_lines":[
               {
                  "title":"WA State Tax",
                  "price":"0.00",
                  "rate":0.065
               },
               {
                  "title":"Seattle Municipal Tax",
                  "price":"0.00",
                  "rate":0.031
               }
            ],
            "origin_location":{
               "id":1986615111,
               "country_code":"US",
               "province_code":"WA",
               "name":"ChefSteps Staging",
               "address1":"1501 Pike Pl, #300",
               "address2":"",
               "city":"Seattle",
               "zip":"98101"
            },
            "destination_location":{
               "id":2055218055,
               "country_code":"US",
               "province_code":"WA",
               "name":"Jeremy Shaffer",
               "address1":"1807 E Howell St",
               "address2":"",
               "city":"Seattle",
               "zip":"98122"
            }
         }
      ],
      "shipping_lines":[
         {
            "id":3493647751,
            "title":"Free standard shipping",
            "price":"0.00",
            "code":"Free standard shipping",
            "source":"shopify",
            "phone":null,
            "requested_fulfillment_service_id":null,
            "delivery_category":null,
            "carrier_identifier":null,
            "tax_lines":[

            ]
         }
      ],
      "billing_address":{
         "first_name":"Jeremy",
         "address1":"1807 E Howell St",
         "phone":null,
         "city":"Seattle",
         "zip":"98122",
         "province":"Washington",
         "country":"United States",
         "last_name":"Shaffer",
         "address2":"",
         "company":null,
         "latitude":47.6174312,
         "longitude":-122.30834,
         "name":"Jeremy Shaffer",
         "country_code":"US",
         "province_code":"WA"
      },
      "shipping_address":{
         "first_name":"Jeremy",
         "address1":"1807 E Howell St",
         "phone":null,
         "city":"Seattle",
         "zip":"98122",
         "province":"Washington",
         "country":"United States",
         "last_name":"Shaffer",
         "address2":"",
         "company":null,
         "latitude":47.6174312,
         "longitude":-122.30834,
         "name":"Jeremy Shaffer",
         "country_code":"US",
         "province_code":"WA"
      },
      "fulfillments":[
         {
            "id":3463384007,
            "order_id":606,
            "status":"success",
            "created_at":"2016-09-01T14:30:03-07:00",
            "service":"manual",
            "updated_at":"2016-09-01T14:30:03-07:00",
            "tracking_company":null,
            "shipment_status":null,
            "tracking_number":null,
            "tracking_numbers":[

            ],
            "tracking_url":null,
            "tracking_urls":[

            ],
            "receipt":{

            },
            "line_items":[
               {
                  "id":7903733191,
                  "variant_id":28299978887,
                  "title":"Shipwire Import Test",
                  "quantity":1,
                  "price":"0.00",
                  "grams":0,
                  "sku":"test10004",
                  "variant_title":"",
                  "vendor":"ChefSteps Staging",
                  "fulfillment_service":"manual",
                  "product_id":8690309639,
                  "requires_shipping":true,
                  "taxable":false,
                  "gift_card":false,
                  "pre_tax_price":"0.00",
                  "name":"Shipwire Import Test",
                  "variant_inventory_management":null,
                  "properties":[

                  ],
                  "product_exists":true,
                  "fulfillable_quantity":0,
                  "total_discount":"0.00",
                  "fulfillment_status":"fulfilled",
                  "tax_lines":[
                     {
                        "title":"WA State Tax",
                        "price":"0.00",
                        "rate":0.065
                     },
                     {
                        "title":"Seattle Municipal Tax",
                        "price":"0.00",
                        "rate":0.031
                     }
                  ],
                  "origin_location":{
                     "id":1986615111,
                     "country_code":"US",
                     "province_code":"WA",
                     "name":"ChefSteps Staging",
                     "address1":"1501 Pike Pl, #300",
                     "address2":"",
                     "city":"Seattle",
                     "zip":"98101"
                  },
                  "destination_location":{
                     "id":2055218055,
                     "country_code":"US",
                     "province_code":"WA",
                     "name":"Jeremy Shaffer",
                     "address1":"1807 E Howell St",
                     "address2":"",
                     "city":"Seattle",
                     "zip":"98122"
                  }
               }
            ]
         },
         {
            "id":3462883207,
            "order_id":606,
            "status":null,
            "created_at":"2016-09-01T13:03:46-07:00",
            "service":"manual",
            "updated_at":"2016-09-01T13:06:27-07:00",
            "tracking_company":null,
            "shipment_status":null,
            "tracking_number":null,
            "tracking_numbers":[

            ],
            "tracking_url":null,
            "tracking_urls":[

            ],
            "receipt":{

            },
            "line_items":[
               {
                  "id":7903733191,
                  "variant_id":28299978887,
                  "title":"Shipwire Import Test",
                  "quantity":1,
                  "price":"0.00",
                  "grams":0,
                  "sku":"test10004",
                  "variant_title":"",
                  "vendor":"ChefSteps Staging",
                  "fulfillment_service":"manual",
                  "product_id":8690309639,
                  "requires_shipping":true,
                  "taxable":false,
                  "gift_card":false,
                  "pre_tax_price":"0.00",
                  "name":"Shipwire Import Test",
                  "variant_inventory_management":null,
                  "properties":[

                  ],
                  "product_exists":true,
                  "fulfillable_quantity":0,
                  "total_discount":"0.00",
                  "fulfillment_status":"fulfilled",
                  "tax_lines":[
                     {
                        "title":"WA State Tax",
                        "price":"0.00",
                        "rate":0.065
                     },
                     {
                        "title":"Seattle Municipal Tax",
                        "price":"0.00",
                        "rate":0.031
                     }
                  ],
                  "origin_location":{
                     "id":1986615111,
                     "country_code":"US",
                     "province_code":"WA",
                     "name":"ChefSteps Staging",
                     "address1":"1501 Pike Pl, #300",
                     "address2":"",
                     "city":"Seattle",
                     "zip":"98101"
                  },
                  "destination_location":{
                     "id":2055218055,
                     "country_code":"US",
                     "province_code":"WA",
                     "name":"Jeremy Shaffer",
                     "address1":"1807 E Howell St",
                     "address2":"",
                     "city":"Seattle",
                     "zip":"98122"
                  }
               }
            ]
         },
         {
            "id":3462864775,
            "order_id":606,
            "status":null,
            "created_at":"2016-09-01T13:00:43-07:00",
            "service":"manual",
            "updated_at":"2016-09-01T13:02:25-07:00",
            "tracking_company":null,
            "shipment_status":null,
            "tracking_number":null,
            "tracking_numbers":[

            ],
            "tracking_url":null,
            "tracking_urls":[

            ],
            "receipt":{

            },
            "line_items":[
               {
                  "id":7903733191,
                  "variant_id":28299978887,
                  "title":"Shipwire Import Test",
                  "quantity":1,
                  "price":"0.00",
                  "grams":0,
                  "sku":"test10004",
                  "variant_title":"",
                  "vendor":"ChefSteps Staging",
                  "fulfillment_service":"manual",
                  "product_id":8690309639,
                  "requires_shipping":true,
                  "taxable":false,
                  "gift_card":false,
                  "pre_tax_price":"0.00",
                  "name":"Shipwire Import Test",
                  "variant_inventory_management":null,
                  "properties":[

                  ],
                  "product_exists":true,
                  "fulfillable_quantity":0,
                  "total_discount":"0.00",
                  "fulfillment_status":"fulfilled",
                  "tax_lines":[
                     {
                        "title":"WA State Tax",
                        "price":"0.00",
                        "rate":0.065
                     },
                     {
                        "title":"Seattle Municipal Tax",
                        "price":"0.00",
                        "rate":0.031
                     }
                  ],
                  "origin_location":{
                     "id":1986615111,
                     "country_code":"US",
                     "province_code":"WA",
                     "name":"ChefSteps Staging",
                     "address1":"1501 Pike Pl, #300",
                     "address2":"",
                     "city":"Seattle",
                     "zip":"98101"
                  },
                  "destination_location":{
                     "id":2055218055,
                     "country_code":"US",
                     "province_code":"WA",
                     "name":"Jeremy Shaffer",
                     "address1":"1807 E Howell St",
                     "address2":"",
                     "city":"Seattle",
                     "zip":"98122"
                  }
               }
            ]
         },
         {
            "id":3462825223,
            "order_id":606,
            "status":null,
            "created_at":"2016-09-01T12:55:06-07:00",
            "service":"manual",
            "updated_at":"2016-09-01T12:58:33-07:00",
            "tracking_company":null,
            "shipment_status":null,
            "tracking_number":null,
            "tracking_numbers":[

            ],
            "tracking_url":null,
            "tracking_urls":[

            ],
            "receipt":{

            },
            "line_items":[
               {
                  "id":7903733191,
                  "variant_id":28299978887,
                  "title":"Shipwire Import Test",
                  "quantity":1,
                  "price":"0.00",
                  "grams":0,
                  "sku":"test10004",
                  "variant_title":"",
                  "vendor":"ChefSteps Staging",
                  "fulfillment_service":"manual",
                  "product_id":8690309639,
                  "requires_shipping":true,
                  "taxable":false,
                  "gift_card":false,
                  "pre_tax_price":"0.00",
                  "name":"Shipwire Import Test",
                  "variant_inventory_management":null,
                  "properties":[

                  ],
                  "product_exists":true,
                  "fulfillable_quantity":0,
                  "total_discount":"0.00",
                  "fulfillment_status":"fulfilled",
                  "tax_lines":[
                     {
                        "title":"WA State Tax",
                        "price":"0.00",
                        "rate":0.065
                     },
                     {
                        "title":"Seattle Municipal Tax",
                        "price":"0.00",
                        "rate":0.031
                     }
                  ],
                  "origin_location":{
                     "id":1986615111,
                     "country_code":"US",
                     "province_code":"WA",
                     "name":"ChefSteps Staging",
                     "address1":"1501 Pike Pl, #300",
                     "address2":"",
                     "city":"Seattle",
                     "zip":"98101"
                  },
                  "destination_location":{
                     "id":2055218055,
                     "country_code":"US",
                     "province_code":"WA",
                     "name":"Jeremy Shaffer",
                     "address1":"1807 E Howell St",
                     "address2":"",
                     "city":"Seattle",
                     "zip":"98122"
                  }
               }
            ]
         }
      ],
      "client_details":{
         "browser_ip":"66.171.190.210",
         "accept_language":"en-US,en;q=0.8",
         "user_agent":"Mozilla\/5.0 (Macintosh; Intel Mac OS X 10_11_6) AppleWebKit\/537.36 (KHTML, like Gecko) Chrome\/52.0.2743.116 Safari\/537.36",
         "session_hash":"496cddbe2fbfc8e24789bc6a056d078f",
         "browser_width":1320,
         "browser_height":799
      },
      "refunds":[

      ],
      "customer":{
         "id":4468086983,
         "email":"customer_5@chefsteps.com",
         "accepts_marketing":false,
         "created_at":"2016-08-22T15:42:44-07:00",
         "updated_at":"2016-09-01T12:51:09-07:00",
         "first_name":"Jeremy",
         "last_name":"Shaffer",
         "orders_count":22,
         "state":"enabled",
         "total_spent":"0.00",
         "last_order_id":606,
         "note":null,
         "verified_email":true,
         "multipass_identifier":"10001",
         "tax_exempt":false,
         "tags":"",
         "last_order_name":"#1318",
         "default_address":{
            "id":4850659591,
            "first_name":"Jeremy",
            "last_name":"Shaffer",
            "company":null,
            "address1":"1807 E Howell St",
            "address2":"",
            "city":"Seattle",
            "province":"Washington",
            "country":"United States",
            "zip":"98122",
            "phone":null,
            "name":"Jeremy Shaffer",
            "province_code":"WA",
            "country_code":"US",
            "country_name":"United States",
            "default":true
         }
      }
   }
}
